{
  "1": {
    "brooktrout": "Jan. 1 - Sept. 30",
    "lakesturgeon": "Jan. 1 - Apr. 30 & July 1 - Dec. 31",
    "laketrout": "Open all year",
    "whitefish": "Open all year",
    "pike": "Open all year",
    "walleye": "Open all year",
    "perch": "Open all year"
  },
  "2": {
    "brooktrout": "Jan. 1 - Labour Day",
    "browntrout": "Open all year",
    "lakesturgeon": "Jan. 1 - Apr. 30 & July 1 - Dec. 31",
    "laketrout": "Jan. 1 - Sept. 30",
    "whitefish": "Open all year",
    "largemouth": "Open all year",
    "smallmouth": "Open all year",
    "muskie": "3rd Sat. in June - Dec. 15",
    "pike": "Open all year",
    "rainbowtrout": "Open all year",
    "splake": "Open all year",
    "bluegill": "Open all year",
    "walleye": "Jan. 1 - Apr. 14 & 3rd Sat. in May - Dec. 31",
    "perch": "Open all year"
  },
  "3": {
    "brooktrout": "Jan. 1 - Sept. 15",
    "lakesturgeon": "Jan. 1 - Apr. 15 & July 1 - Dec. 31",
    "laketrout": "Jan. 1 - Sept. 30",
    "whitefish": "Open all year",
    "largemouth": "Open all year",
    "smallmouth": "Open all year",
    "pike": "Open all year",
    "splake": "Open all year",
    "bluegill": "Open all year",
    "walleye": "Jan. 1 - Apr. 14 & 3rd Sat. in May - Dec. 31",
    "perch": "Open all year"
  },
  "4": {
    "brooktrout": "Jan. 1 - Labour Day",
    "crappie": "Open all year",
    "laketrout": "Jan. 1 - Sept. 30",
    "whitefish": "Open all year",
    "largemouth": "Open all year",
    "smallmouth": "Open all year",
    "muskie": "3rd Sat. in June - Dec. 15",
    "pike": "Open all year",
    "rainbowtrout": "Open all year",
    "splake": "Open all year",
    "bluegill": "Open all year",
    "walleye": "Jan. 1 - Apr. 14 & 3rd Sat. in May - Dec. 31",
    "perch": "Open all year"
  },
  "5": {
    "brooktrout": "Open all year",
    "browntrout": "Open all year",
    "crappie": "Open all year",
    "laketrout": "Jan. 1 - Sept. 30",
    "whitefish": "Open all year",
    "largemouth": "Open all year",
    "smallmouth": "Open all year",
    "muskie": "3rd Sat. in June - Dec. 15",
    "pike": "Open all year",
    "rainbowtrout": "Open all year",
    "splake": "Open all year",
    "bluegill": "Open all year",
    "walleye": "Jan. 1 - Apr. 14 & 3rd Sat. in May - Dec. 31",
    "perch": "Open all year"
  },
  "6": {
    "atlanticsalmon": "Open all year",
    "brooktrout": "4th Sat. in Apr. - Labour Day",
    "browntrout": "Open all year",
    "catfish": "Open all year",
    "crappie": "Open all year",
    "laketrout": "Jan. 1 - Sept. 30",
    "whitefish": "Open all year",
    "largemouth": "Open all year",
    "smallmouth": "Open all year",
    "muskie": "3rd Sat. in June - Dec. 15",
    "pike": "Open all year",
    "pacificsalmon": "Open all year",
    "rainbowtrout": "Open all year",
    "splake": "Open all year",
    "bluegill": "Open all year",
    "walleye": "Jan. 1 - Apr. 14 & 3rd Sat. in May - Dec. 31",
    "perch": "Open all year"
  },
  "7": {
    "atlanticsalmon": "Open all year",
    "brooktrout": "Jan. 1 - Labour Day",
    "browntrout": "Open all year",
    "laketrout": "Jan. 1 - Sept. 30",
    "whitefish": "Open all year",
    "largemouth": "Open all year",
    "smallmouth": "Open all year",
    "pike": "Open all year",
    "pacificsalmon": "Open all year",
    "rainbowtrout": "Open all year",
    "splake": "Open all year",
    "bluegill": "Open all year",
    "walleye": "Jan. 1 - Apr. 14 & 3rd Sat. in May - Dec. 31",
    "perch": "Open all year"
  },
  "8": {
    "brooktrout": "Jan. 1 - Sept. 15",
    "lakesturgeon": "Jan. 1 - Apr. 30 & July 1 - Dec. 31",
    "laketrout": "Feb. 15 - Mar. 15 & 3rd Sat. in May - Sept. 30",
    "whitefish": "Open all year",
    "largemouth": "Open all year",
    "smallmouth": "Open all year",
    "pike": "Open all year",
    "rainbowtrout": "Open all year",
    "splake": "Open all year",
    "bluegill": "Open all year",
    "walleye": "Jan. 1 - Apr. 14 & 3rd Sat. in May - Dec. 31",
    "perch": "Open all year"
  },
  "9": {
    "atlanticsalmon": "Open all year",
    "brooktrout": "4th Sat. in Apr. - Labour Day",
    "browntrout": "Open all year",
    "catfish": "Open all year",
    "crappie": "Open all year",
    "laketrout": "Jan. 1 - Sept. 30",
    "whitefish": "Open all year",
    "largemouth": "Open all year",
    "smallmouth": "Open all year",
    "muskie": "3rd Sat. in June - Dec. 15",
    "pike": "Open all year",
    "pacificsalmon": "Open all year",
    "rainbowtrout": "Open all year",
    "splake": "Jan. 1 - Sept. 30",
    "bluegill": "Open all year",
    "walleye": "Jan. 1 - Apr. 14 & 3rd Sat. in May - Dec. 31",
    "perch": "Open all year"
  },
  "10": {
    "atlanticsalmon": "Jan. 1 - Sept. 30",
    "brooktrout": "Jan. 1 - Sept. 30",
    "browntrout": "Open all year",
    "catfish": "Open all year",
    "crappie": "Open all year",
    "laketrout": "Jan. 1 - Labour Day",
    "whitefish": "Open all year",
    "largemouth": "3rd Saturday in June - November 30",
    "smallmouth": "3rd Saturday in June - November 30",
    "muskie": "3rd Sat. in June - Dec. 15",
    "pike": "Open all year",
    "pacificsalmon": "Open all year",
    "rainbowtrout": "Open all year",
    "splake": "Open all year",
    "bluegill": "Open all year",
    "walleye": "January 1 to the third Sunday in March and third Saturday in May to December 31",
    "perch": "Open all year"
  },
  "11": {
    "brooktrout": "Feb. 15 - Sept. 30",
    "browntrout": "4th Sat. in Apr. - Sept. 30",
    "catfish": "Open all year",
    "crappie": "Open all year",
    "laketrout": "February 15 to third Sunday in March and third Saturday in May to Labour Day",
    "whitefish": "Open all year",
    "largemouth": "January 1 to third Sunday in March and third Saturday in May to December 31",
    "smallmouth": "January 1 to third Sunday in March and third Saturday in May to December 31",
    "muskie": "3rd Sat. in June - Dec. 15",
    "pike": "Jan. 1 - 3rd Sun. in Mar. & 3rd Sat. in May - Dec. 31",
    "pacificsalmon": "Open all year",
    "rainbowtrout": "Open all year",
    "splake": "Open all year",
    "bluegill": "Open all year",
    "walleye": "Jan. 1 - 3rd Sun. in Mar. & 3rd Sat. in May - Dec. 31",
    "perch": "Open all year"
  },
  "12": {
    "atlanticsalmon": "Fri. before 4th Sat. in Apr. - Sept. 30",
    "brooktrout": "Fri. before 4th Sat. in Apr. - Sept. 30",
    "browntrout": "Fri. before 4th Sat. in Apr. - Sept. 30",
    "catfish": "Open all year",
    "crappie": "Open all year",
    "laketrout": "Fri. before 4th Sat. in Apr. - Sept. 30",
    "whitefish": "Open all year",
    "largemouth": "Fri. before 4th Sat. in June - Nov. 30",
    "smallmouth": "Fri. before 4th Sat. in June - Nov. 30",
    "muskie": "Fri. before 3rd Sat. in June - Dec. 15",
    "pike": "Jan. 1 - Mar. 31 & Fri. before 3rd Sat. in May - Dec. 31",
    "rainbowtrout": "Fri. before 4th Sat. in Apr. - Sept. 30",
    "splake": "Fri. before 4th Sat. in Apr. - Sept. 30",
    "bluegill": "Open all year",
    "walleye": "Jan. 1 - Mar. 31 & Fri. before 3rd Sat. in May - Dec. 31",
    "perch": "Open all year"
  },
  "13": {
    "atlanticsalmon": "Open all year",
    "browntrout": "Open all year",
    "catfish": "Open all year",
    "crappie": "Open all year",
    "laketrout": "Jan. 1 - Sept. 30 & Dec. 1 - Dec. 31",
    "whitefish": "Open all year",
    "largemouth": "4th Sat. in June - Nov. 30",
    "smallmouth": "4th Sat. in June - Nov. 30",
    "muskie": "3rd Sat. in June - Dec. 15",
    "pike": "Open all year",
    "pacificsalmon": "Open all year",
    "rainbowtrout": "Open all year",
    "bluegill": "Open all year",
    "walleye": "Open all year",
    "perch": "Open all year"
  },
  "14": {
    "atlanticsalmon": "Open all year",
    "browntrout": "Open all year",
    "catfish": "Open all year",
    "crappie": "Open all year",
    "lakeherringcisco": "Open all year",
    "laketrout": "Jan. 1 - Sept. 30 & Dec. 1 - Dec. 31",
    "whitefish": "Open all year",
    "largemouth": "4th Sat. in June - Nov. 30",
    "smallmouth": "4th Sat. in June - Nov. 30",
    "muskie": "3rd Sat. in June - Dec. 15",
    "pike": "Jan. 1 - Mar. 1 & May 1 - Dec. 31",
    "pacificsalmon": "Open all year",
    "rainbowtrout": "Open all year",
    "bluegill": "Open all year",
    "walleye": "Jan. 1 - Mar. 1 & May 1 - Dec. 31",
    "perch": "Open all year"
  },
  "15": {
    "brooktrout": "Jan. 1 - Sept. 30",
    "browntrout": "Open all year",
    "catfish": "Open all year",
    "crappie": "Open all year",
    "laketrout": "Jan. 1 - Sept. 30",
    "whitefish": "Open all year",
    "largemouth": "4th Sat. in June - Nov. 30",
    "smallmouth": "4th Sat. in June - Nov. 30",
    "muskie": "1st Sat. in June - Dec. 15",
    "pike": "Jan. 1 - Mar. 31 & 3rd Sat. in May - Dec. 31",
    "pacificsalmon": "Open all year",
    "rainbowtrout": "Open all year",
    "splake": "Open all year",
    "bluegill": "Open all year",
    "walleye": "Jan. 1 - Mar. 15 & 3rd Sat. in May - Dec. 31",
    "perch": "Open all year"
  },
  "16": {
    "atlanticsalmon": "4th Sat. in Apr. to Sept 30",
    "brooktrout": "4th Sat. in Apr. - Sept. 30",
    "browntrout": "4th Sat. in Apr. - Sept. 30",
    "catfish": "Open all year",
    "crappie": "Open all year",
    "laketrout": "Jan. 1 - Sept. 30",
    "whitefish": "Open all year",
    "largemouth": "4th Sat. in June - Nov. 30",
    "smallmouth": "4th Sat. in June - Nov. 30",
    "muskie": "1st Sat. in June - Dec. 15",
    "pike": "Jan. 1 - Mar. 31 & 2nd Sat. in May - Dec. 31",
    "pacificsalmon": "4th Sat. in Apr. - Sept. 30",
    "rainbowtrout": "4th Sat. in Apr. - Sept. 30",
    "splake": "Open all year",
    "bluegill": "Open all year",
    "walleye": "Jan. 1 - Mar. 15 & 2nd Sat. in May - Dec. 31",
    "perch": "Open all year"
  },
  "17": {
    "atlanticsalmon": "4th Sat. in Apr. to Sept 30",
    "brooktrout": "4th Sat. in Apr. - Sept. 30",
    "browntrout": "4th Sat. in Apr. - Sept. 30",
    "catfish": "4th Sat. in Apr. - Nov. 15",
    "crappie": "Open all year",
    "laketrout": "4th Sat. in Apr. - Sept. 30",
    "whitefish": "4th Sat. in Apr. - Nov. 15",
    "largemouth": "3rd Sat. in June - Dec. 15",
    "smallmouth": "3rd Sat. in June - Dec. 15",
    "muskie": "1st Sat. in June - Dec. 15",
    "pike": "Open all year",
    "pacificsalmon": "4th Sat. in Apr. - Sept. 30",
    "rainbowtrout": "4th Sat. in Apr. - Sept. 30",
    "bluegill": "Open all year",
    "walleye": "2nd Sat. in May - Nov. 15",
    "perch": "Open all year"
  },
  "18": {
    "brooktrout": "Open all year",
    "browntrout": "Open all year",
    "catfish": "Open all year",
    "crappie": "Open all year",
    "laketrout": "4th Sat. in May - Sept. 8",
    "whitefish": "Open all year",
    "largemouth": "3rd Sat. in June - Dec. 15",
    "smallmouth": "3rd Sat. in June - Dec. 15",
    "muskie": "1st Sat. in June - Dec. 15",
    "pike": "Jan. 1 - Mar. 31 & 2nd Sat. in May - Dec. 31",
    "pacificsalmon": "Open all year",
    "rainbowtrout": "Open all year",
    "splake": "Open all year",
    "bluegill": "Open all year",
    "walleye": "Jan. 1 - Mar. 1 & 2nd Sat. in May - Dec. 31",
    "perch": "Open all year"
  },
  "19": {
    "atlanticsalmon": "Open all year",
    "browntrout": "Open all year",
    "catfish": "Open all year",
    "crappie": "Open all year",
    "laketrout": "Jan. 1 - Sept. 30 & Dec. 1 - Dec. 31",
    "whitefish": "Open all year",
    "largemouth": "4th Sat. in June - Nov. 30",
    "smallmouth": "4th Sat. in June - Nov. 30",
    "muskie": "1st Sat. in June - Dec. 15",
    "pike": "Open all year",
    "pacificsalmon": "Open all year",
    "rainbowtrout": "Open all year",
    "bluegill": "Open all year",
    "walleye": "Open all year",
    "perch": "Open all year"
  },
  "20": {
    "atlanticsalmon": "Open all year",
    "browntrout": "Open all year",
    "catfish": "Open all year",
    "crappie": "Open all year",
    "laketrout": "Jan. 1 - Sept. 30 & Dec. 1 - Dec. 31",
    "whitefish": "Open all year",
    "largemouth": "Third Saturday in June to December 31",
    "muskie": "3rd Sat. in June - Dec. 15",
    "pike": "Jan. 1 - Mar. 31 & 1st Sat. in May - Dec. 31",
    "pacificsalmon": "Open all year",
    "rainbowtrout": "Open all year",
    "smallmouth": "First Saturday in July to December 31",
    "bluegill": "Open all year",
    "walleye": "Jan. 1 - Mar.1 & the 1st Sat. in May - Dec. 31",
    "perch": "Open all year"
  }
}